emloop_tensorflow/__init__.py
emloop_tensorflow/frozen_model.py
emloop_tensorflow/graph_tower.py
emloop_tensorflow/model.py
emloop_tensorflow/hooks/__init__.py
emloop_tensorflow/hooks/decay_lr.py
emloop_tensorflow/hooks/init_lr.py
emloop_tensorflow/hooks/write_tensorboard.py
emloop_tensorflow/metrics/__init__.py
emloop_tensorflow/metrics/bin.py
emloop_tensorflow/models/__init__.py
emloop_tensorflow/models/blocks.py
emloop_tensorflow/models/conv.py
emloop_tensorflow/models/conv_blocks.py
emloop_tensorflow/models/rnn.py
emloop_tensorflow/models/rnn_blocks.py
emloop_tensorflow/ops/__init__.py
emloop_tensorflow/ops/flatten3d.py
emloop_tensorflow/ops/loss.py
emloop_tensorflow/ops/repeat.py
emloop_tensorflow/ops/sequence.py
emloop_tensorflow/ops/sparse.py
emloop_tensorflow/third_party/__init__.py
emloop_tensorflow/third_party/tensorflow/__init__.py
emloop_tensorflow/third_party/tensorflow/average_gradients.py
emloop_tensorflow/third_party/tensorflow/freeze_graph.py
emloop_tensorflow/utils/__init__.py
emloop_tensorflow/utils/profiler.py
emloop_tensorflow/utils/reflection.py
emloop_tensorflow-0.6.0.dist-info/LICENSE
emloop_tensorflow-0.6.0.dist-info/METADATA
emloop_tensorflow-0.6.0.dist-info/WHEEL
emloop_tensorflow-0.6.0.dist-info/top_level.txt
emloop_tensorflow-0.6.0.dist-info/RECORD
