Metadata-Version: 2.1
Name: emloop-tensorflow
Version: 0.6.0
Summary: TensorFlow extension for emloop.
Home-page: https://github.com/iterait/emloop-tensorflow
Author: Iterait a.s.
Author-email: hello@iterait.com
License: MIT
Keywords: tensorflow wrapper
Platform: UNKNOWN
Classifier: Development Status :: 4 - Beta
Classifier: Environment :: Console
Classifier: Intended Audience :: Developers
Classifier: Intended Audience :: Education
Classifier: Intended Audience :: Science/Research
Classifier: Operating System :: Unix
Classifier: Programming Language :: Python :: Implementation :: CPython
Classifier: Topic :: Scientific/Engineering :: Artificial Intelligence
Classifier: License :: OSI Approved :: MIT License
Classifier: Programming Language :: Python :: 3.5
Classifier: Programming Language :: Python :: 3.6
Requires-Dist: tensorflow-estimator (>=1.13)
Requires-Dist: emloop (>=0.2.0)
Requires-Dist: numpy (>=1.16)
